<?xml version="1.0" encoding="utf-8" ?>
<LanguageData>

	<TiberiumResearchBench.label>tiberium research station</TiberiumResearchBench.label>
	<TiberiumResearchBench.description>A specialized research bench for Tiberium technologies.\n\nResearch is sped up by the high-tech tools.\n\nRequires power.</TiberiumResearchBench.description>
	
	<TiberiumResearchCraftingBench.label>Tiberium research crafting adapter</TiberiumResearchCraftingBench.label>
	<TiberiumResearchCraftingBench.description>This building allows the crafting of Tiberium information items.</TiberiumResearchCraftingBench.description>
	

</LanguageData>